README.md
html_template.html
scheduled_tasks_reader.py
setup.py
scheduled_tasks_reader.egg-info/PKG-INFO
scheduled_tasks_reader.egg-info/SOURCES.txt
scheduled_tasks_reader.egg-info/dependency_links.txt
scheduled_tasks_reader.egg-info/entry_points.txt
scheduled_tasks_reader.egg-info/requires.txt
scheduled_tasks_reader.egg-info/top_level.txt