Metadata-Version: 2.1
Name: scheduled-tasks-reader
Version: 0.1.1
Summary: A program to various information of scheduled tasks.
Home-page: UNKNOWN
Author: UL15
Author-email: FerienInThailand15@protonmail.com
License: MIT
Platform: UNKNOWN
